{"critical":"<link rel=\"preload\" as=\"image\" type=\"image\/webp\" href=\"\/assets\/img\/products\/eyelash-serum\/hero\/slides\/slide-1\/nanolash-eyelash-serum-header@xs.webp\" media=\"(min-width: 0px) and (max-width: 575.98px)\">\r\n        <link rel=\"preload\" as=\"image\" type=\"image\/webp\" href=\"\/assets\/img\/products\/eyelash-serum\/hero\/slides\/slide-1\/nanolash-eyelash-serum-header@sm.webp\" media=\"(min-width: 576px) and (max-width: 767.98px)\">\r\n        <link rel=\"preload\" as=\"image\" type=\"image\/webp\" href=\"\/assets\/img\/products\/eyelash-serum\/hero\/slides\/slide-1\/nanolash-eyelash-serum-header@md.webp\" media=\"(min-width: 768px) and (max-width: 991.98px)\">\r\n        <link rel=\"preload\" as=\"image\" type=\"image\/webp\" href=\"\/assets\/img\/products\/eyelash-serum\/hero\/slides\/slide-1\/nanolash-eyelash-serum-header@lg.webp\" media=\"(min-width: 992px) and (max-width: 1399.98px)\">\r\n        <link rel=\"preload\" as=\"image\" type=\"image\/webp\" href=\"\/assets\/img\/products\/eyelash-serum\/hero\/slides\/slide-1\/nanolash-eyelash-serum-header@xxl.webp\" media=\"(min-width: 1400px)\">","hero":{"dots":[{"type":"image","src":"\/assets\/img\/products\/eyelash-serum\/hero\/dots\/nanolash-eyelash-serum-header-1"},{"type":"image","src":"\/assets\/img\/products\/eyelash-serum\/hero\/dots\/nanolash-eyelash-serum-header-2"},{"type":"image","src":"\/assets\/img\/products\/eyelash-serum\/hero\/dots\/nanolash-eyelash-serum-header-3"},{"type":"image","src":"\/assets\/img\/products\/eyelash-serum\/hero\/dots\/nanolash-eyelash-serum-header-4"}],"slides":[{"alt":"test1","extension":"png","src":"\/assets\/img\/products\/eyelash-serum\/hero\/slides\/slide-1\/nanolash-eyelash-serum-header"},{"alt":"test2","extension":"png","src":"\/assets\/img\/products\/eyelash-serum\/hero\/slides\/slide-2\/nanolash-eyelash-serum-header"},{"alt":"test3","extension":"png","src":"\/assets\/img\/products\/eyelash-serum\/hero\/slides\/slide-3\/nanolash-eyelash-serum-header"},{"alt":"test4","extension":"png","src":"\/assets\/img\/products\/eyelash-serum\/hero\/slides\/slide-4\/nanolash-eyelash-serum-header"}]},"icons":["\/assets\/img\/products\/eyelash-serum\/nanolash-eyelash-serum-icon-1","\/assets\/img\/products\/eyelash-serum\/nanolash-eyelash-serum-icon-2","\/assets\/img\/products\/eyelash-serum\/nanolash-eyelash-serum-icon-3","\/assets\/img\/products\/eyelash-serum\/nanolash-eyelash-serum-icon-4"],"first_order_section":{"background":{"src":"\/assets\/img\/products\/eyelash-serum\/parallax\/nanolash-eyelash-serum-parallax-front","extension":"png"},"parallax":{"front":{"src":"\/assets\/img\/products\/eyelash-serum\/parallax\/nanolash-eyelash-serum-parallax-front","extension":"png"},"back":{"src":"\/assets\/img\/products\/eyelash-serum\/parallax\/nanolash-eyelash-serum-parallax-back","extension":"png"}}},"gallery":"\/assets\/img\/products\/eyelash-serum\/gallery\/nanolash-eyelash-serum-gallery","second_order_section":{"background":{"src":"\/assets\/img\/products\/eyelash-serum\/nanolash-eyelash-serum-order-bg","extension":"jpg"}},"product_effects":{"type":"slider","before":{"src":"\/assets\/img\/products\/eyelash-serum\/effects\/nanolash-eyelash-serum-effects-before","alt":"effect before"},"after":{"src":"\/assets\/img\/products\/eyelash-serum\/effects\/nanolash-eyelash-serum-effects-after","alt":"effect after"}}}